LogGrap/__init__.py
LogGrap-0.1.9.dist-info/LICENSE
LogGrap-0.1.9.dist-info/METADATA
LogGrap-0.1.9.dist-info/WHEEL
LogGrap-0.1.9.dist-info/top_level.txt
LogGrap-0.1.9.dist-info/RECORD
