Metadata-Version: 2.1
Name: LogGrap
Version: 0.1.9
Summary: A logging package for your python project.
Author-email: ssomgrap <ssomgrap@gmail.com>
Project-URL: Homepage, https://github.com/SsomGrap/LogGrap
Project-URL: Bug Tracker, https://github.com/SsomGrap/LogGrap/issues
Classifier: Programming Language :: Python :: 3
Classifier: License :: OSI Approved :: MIT License
Classifier: Operating System :: OS Independent
Requires-Python: >=3.7
License-File: LICENSE
